Metadata-Version: 1.2
Name: RawProc
Version: 0.0.1
Summary: RAW image converter
Home-page: https://github.com/Biblbrox/RawConverter
Author: Aleksey Kuchkov
Author-email: biblbroxxx@gmail.com
License: UNKNOWN
Download-URL: https://github.com/Biblbrox/RawConverter/archive/0.0.1.tar.gz
Platform: UNKNOWN
Classifier: Programming Language :: Python :: 3
Classifier: License :: OSI Approved :: GNU General Public License v3 (GPLv3)
Classifier: Operating System :: OS Independent
Requires-Python: >=3.6
